pyrole/Interaction.py
pyrole/__init__.py
pyrole/axisviewer.py
pyrole/physics.py
pyrole/images/astar.gif
pyrole/images/b1.png
pyrole/images/b2.png
pyrole/images/b3.png
pyrole/images/b4.png
pyrole/images/b5.png
pyrole/images/b6.png
pyrole/images/b7.png
pyrole/images/bg.png
pyrole/images/bstar.gif
pyrole/images/earth.png
pyrole/images/fstar.gif
pyrole/images/gstar.gif
pyrole/images/icon.jpg
pyrole/images/jupiter.png
pyrole/images/kstar.gif
pyrole/images/mars.png
pyrole/images/mercury.png
pyrole/images/moon.png
pyrole/images/mstar.gif
pyrole/images/neptune.png
pyrole/images/ostar.gif
pyrole/images/p1.png
pyrole/images/p2.png
pyrole/images/p3.png
pyrole/images/p4.png
pyrole/images/saturn.png
pyrole/images/uranus.png
pyrole/images/venus.png
pyrole/images/wstar.gif
pyrole-0.1.1.dist-info/METADATA
pyrole-0.1.1.dist-info/WHEEL
pyrole-0.1.1.dist-info/top_level.txt
pyrole-0.1.1.dist-info/RECORD
