Metadata-Version: 2.1
Name: pyrole
Version: 0.1.1
Summary: 这个模块可以让你的代码变得更简单
Home-page: https://stevena.rth10.com/pyrole
Author: StevenA
Author-email: stevena_star@qq.com
Project-URL: Documentation, https://b23.tv/vHelxyv
Project-URL: Bug Tracker, https://b23.tv/vHelxyv
Classifier: Programming Language :: Python :: 3
Classifier: License :: OSI Approved :: MIT License
Classifier: Operating System :: OS Independent
Classifier: Topic :: Utilities
Classifier: Programming Language :: Python :: 3.9
Requires-Python: >=3.9
Requires-Dist: Pillow >=8.4.0
